uncertainty_toolbox/__init__.py
uncertainty_toolbox/data.py
uncertainty_toolbox/matplotlibrc
uncertainty_toolbox/metrics.py
uncertainty_toolbox/metrics_accuracy.py
uncertainty_toolbox/metrics_calibration.py
uncertainty_toolbox/metrics_scoring_rule.py
uncertainty_toolbox/recalibration.py
uncertainty_toolbox/utils.py
uncertainty_toolbox/viz.py
uncertainty_toolbox-0.1.1.dist-info/LICENSE
uncertainty_toolbox-0.1.1.dist-info/WHEEL
uncertainty_toolbox-0.1.1.dist-info/METADATA
uncertainty_toolbox-0.1.1.dist-info/RECORD
