Metadata-Version: 2.1
Name: uncertainty-toolbox
Version: 0.1.1
Summary: Uncertainty Toolbox: a python toolbox for predictive uncertainty quantification, calibration, metrics, and visualization.
Author: Willie Neiswanger, Youngseog Chung, Ian Char, Han Guo
Author-email: willie.neiswanger@gmail.com
Requires-Python: >=3.6
Classifier: Programming Language :: Python :: 3
Classifier: License :: OSI Approved :: MIT License
Classifier: Operating System :: OS Independent
Requires-Dist: numpy>=1.19.0
Requires-Dist: scipy>=1.5.0
Requires-Dist: matplotlib>=3.2.2
Requires-Dist: scikit-learn>=0.23.1
Requires-Dist: tqdm>=4.54.0
Project-URL: Documentation, https://uncertainty-toolbox.github.io/docs/
Project-URL: Github, https://github.com/uncertainty-toolbox/uncertainty-toolbox
Project-URL: Home, https://uncertainty-toolbox.github.io/
